churchkey/__init__.py
churchkey/__main__.py
churchkey-1.1.5.dist-info/LICENSE.txt
churchkey-1.1.5.dist-info/METADATA
churchkey-1.1.5.dist-info/WHEEL
churchkey-1.1.5.dist-info/entry_points.txt
churchkey-1.1.5.dist-info/top_level.txt
churchkey-1.1.5.dist-info/RECORD
