Metadata-Version: 2.1
Name: churchkey
Version: 1.1.5
Summary: a tool tunneling ssh over http proxy;
Home-page: https://github.com/cykerway/churchkey
Author: Cyker Way
Author-email: cykerway@example.com
License: UNKNOWN
Project-URL: Funding, https://paypal.me/cykerway
Project-URL: Source, https://github.com/cykerway/churchkey/
Project-URL: Tracker, https://github.com/cykerway/churchkey/issues
Keywords: ssh,http,proxy,network
Platform: UNKNOWN
Classifier: Development Status :: 4 - Beta
Classifier: Intended Audience :: End Users/Desktop
Classifier: License :: OSI Approved :: GNU General Public License v3 (GPLv3)
Classifier: Programming Language :: Python :: 3.10
Classifier: Programming Language :: Python :: 3.6
Classifier: Programming Language :: Python :: 3.7
Classifier: Programming Language :: Python :: 3.8
Classifier: Programming Language :: Python :: 3.9
Classifier: Topic :: System
Requires-Dist: argparse-ext
